{
  "artifact_id": "three_channel_v1_metric_results",
  "status": "internal_v1_recompute",
  "method": {
    "source": "V0 evaluated claims plus SAS-V1-002 calibration decisions",
    "primary_horizon": "7d",
    "level_aware_rr_available": false,
    "multimodal_customer_claims_included": false,
    "bulk_market_database_used": false,
    "external_delivery_approved": false
  },
  "totals": {
    "public_text_rows": 1534,
    "v1_evaluable_claims": 170,
    "confirmed_hits": 93,
    "contradicted_misses": 77,
    "review_false_negative_pending": 5
  },
  "channel_summaries": [
    {
      "source_id": "bablos79",
      "public_text_rows": 528,
      "v0_evaluable_claims": 19,
      "v1_evaluable_claims": 14,
      "confirmed_hits": 9,
      "contradicted_misses": 5,
      "primary_hit_rate": "64.285714",
      "avg_directional_return_pct": "0.742848",
      "avg_mfe_pct": "3.637653",
      "avg_mae_pct": "-3.060955",
      "rr_available_count": 0,
      "provider_coverage": {
        "binance": {
          "claim_count": 1,
          "symbols": [
            "BTCUSDT"
          ]
        },
        "moex_iss": {
          "claim_count": 13,
          "symbols": [
            "CHMF",
            "GAZP",
            "LENT",
            "MAGN",
            "PHOR",
            "SBER",
            "SFIN",
            "SMLT",
            "X5"
          ]
        }
      },
      "exclusion_counts": {
        "not_market_related": 384,
        "no_text": 63,
        "no_supported_asset_or_proxy": 75,
        "mixed_direction": 11,
        "no_direction": 38,
        "review_false_positive": 2,
        "review_needs_context": 3,
        "review_false_negative_pending": 0,
        "unreviewed_media_excluded": 0
      },
      "review_decision_counts": {
        "false_positive": 2,
        "accepted": 2,
        "needs_context": 3,
        "accepted_unreviewed": 13
      },
      "delta_from_v0": {
        "evaluable_claims": -5,
        "confirmed_hits": -2,
        "contradicted_misses": -3
      },
      "review_false_negative_pending": 0
    },
    {
      "source_id": "nemphiscrypts",
      "public_text_rows": 514,
      "v0_evaluable_claims": 53,
      "v1_evaluable_claims": 49,
      "confirmed_hits": 28,
      "contradicted_misses": 21,
      "primary_hit_rate": "57.142857",
      "avg_directional_return_pct": "0.434858",
      "avg_mfe_pct": "7.991959",
      "avg_mae_pct": "-7.354706",
      "rr_available_count": 0,
      "provider_coverage": {
        "binance": {
          "claim_count": 49,
          "symbols": [
            "ARBUSDT",
            "AVAXUSDT",
            "BTCUSDT",
            "DOTUSDT",
            "ETHUSDT",
            "SOLUSDT",
            "SUIUSDT"
          ]
        }
      },
      "exclusion_counts": {
        "no_direction": 17,
        "no_supported_asset_or_proxy": 128,
        "not_market_related": 291,
        "mixed_direction": 32,
        "no_text": 15,
        "review_needs_context": 3,
        "review_false_positive": 1,
        "review_false_negative_pending": 2,
        "unreviewed_media_excluded": 0
      },
      "review_decision_counts": {
        "accepted": 3,
        "needs_context": 3,
        "false_positive": 1,
        "accepted_unreviewed": 46
      },
      "delta_from_v0": {
        "evaluable_claims": -4,
        "confirmed_hits": -3,
        "contradicted_misses": -1
      },
      "review_false_negative_pending": 2
    },
    {
      "source_id": "pifagortrade",
      "public_text_rows": 492,
      "v0_evaluable_claims": 112,
      "v1_evaluable_claims": 107,
      "confirmed_hits": 56,
      "contradicted_misses": 51,
      "primary_hit_rate": "52.336449",
      "avg_directional_return_pct": "-0.153127",
      "avg_mfe_pct": "6.309542",
      "avg_mae_pct": "-7.010254",
      "rr_available_count": 0,
      "provider_coverage": {
        "binance": {
          "claim_count": 107,
          "symbols": [
            "BTCUSDT",
            "DOTUSDT",
            "ETHUSDT",
            "TONUSDT"
          ]
        }
      },
      "exclusion_counts": {
        "no_direction": 28,
        "no_text": 5,
        "no_supported_asset_or_proxy": 162,
        "not_market_related": 133,
        "mixed_direction": 90,
        "review_needs_context": 3,
        "review_false_positive": 3,
        "review_false_negative_pending": 3,
        "unreviewed_media_excluded": 0
      },
      "review_decision_counts": {
        "needs_context": 3,
        "false_positive": 3,
        "accepted_unreviewed": 108
      },
      "delta_from_v0": {
        "evaluable_claims": -5,
        "confirmed_hits": -4,
        "contradicted_misses": -1
      },
      "review_false_negative_pending": 3
    }
  ],
  "kept_claim_ids_by_channel": {
    "bablos79": [
      "claim_f6041f3dfd9af816",
      "claim_0de8e67e509e128e",
      "claim_b27ba11d5d1fd8d4",
      "claim_542e6a1f0b927f16",
      "claim_978ab5fe7d47513e",
      "claim_e7604b543021149b",
      "claim_5d4c7f959eeca62a",
      "claim_cacb5426e1d04029",
      "claim_f94afc27b13ab0a8",
      "claim_8331084bac80fa60",
      "claim_27a73054d5007c7c",
      "claim_0315cdc675ad90fd",
      "claim_62e4b40fd79234a3",
      "claim_7855b6dfcd530efa",
      "claim_698efc105529b9a7"
    ],
    "nemphiscrypts": [
      "claim_7997845104759b60",
      "claim_e833a59202e9b6d9",
      "claim_1075e7995bd09e6d",
      "claim_f7c9b3264ae96705",
      "claim_87f38bf8642f6a08",
      "claim_81fda48ddddf544e",
      "claim_b3bdd612a4dca13b",
      "claim_9c153d995f402e96",
      "claim_de72b68fc133c4d0",
      "claim_4304614a653f28f9",
      "claim_b0c537f1a32042f3",
      "claim_0fa3f0be0899dd0f",
      "claim_64f8036735ddb3b2",
      "claim_7baad009edae819a",
      "claim_57dc7a01f9d9e8b8",
      "claim_866b1c04d108fc2c",
      "claim_16aabb6678ef2d11",
      "claim_7cedcfd56c99c4c3",
      "claim_d1a124c641ab88b6",
      "claim_8723b6e4fd945c28",
      "claim_4c13cc523e6bf6dc",
      "claim_0754a427ef421703",
      "claim_ed0f1ee93ba28dc9",
      "claim_e56118325c3dc3e9",
      "claim_99ffa8c1a52db6f7",
      "claim_922e2d0ce7386dcf",
      "claim_3359af7a823ab130",
      "claim_0cb6aa3d10fb1939",
      "claim_7cd30002abba1574",
      "claim_9183a3888c9287fd",
      "claim_5921c353b1e3c6e0",
      "claim_aa66ac4d06dfe853",
      "claim_c5d8bf6a351ba91e",
      "claim_db34ed04e58cec2c",
      "claim_6fdaef104c350419",
      "claim_2ec2ca852fb6f775",
      "claim_dece89ff5a2346d8",
      "claim_dc68de28b1dfa4bc",
      "claim_b3d042ffb79bbce4",
      "claim_d240b717da85932a",
      "claim_8e2fece7308a7922",
      "claim_9cfa15e99c15f918",
      "claim_1ce3aaefbc5c3d3f",
      "claim_5aba1ed3996aad40",
      "claim_7df6a234a8e3fbde",
      "claim_49bfc5806760ec05",
      "claim_30cee5a156b0c666",
      "claim_d2583a6e569da950",
      "claim_3a02731c67268db7"
    ],
    "pifagortrade": [
      "claim_413df3d46a002e05",
      "claim_eca3d855ec360852",
      "claim_7f517f59bb3cc92a",
      "claim_341c325f34e561b1",
      "claim_8a3556eeedc961aa",
      "claim_4a59c1bc0c0b088a",
      "claim_25549dda3c552b05",
      "claim_d8b6267eb5701866",
      "claim_3ca933a7565b8234",
      "claim_91cdd4a53184a52a",
      "claim_a9f9dbcb2c5a2915",
      "claim_a45ae08bd3055457",
      "claim_5d86c13c424da70c",
      "claim_251458bdfc984b2c",
      "claim_f7398176d112a4e9",
      "claim_43317a77290a7a3a",
      "claim_2f93e8a5515ebb18",
      "claim_85d6ff8102481d20",
      "claim_5c5190039f9f7015",
      "claim_61cefb445583c1f9",
      "claim_f50f64fcf68579c0",
      "claim_db19a767ac84bdc7",
      "claim_7f790afe24136fe2",
      "claim_4012b23e81643dfd",
      "claim_004d5028607a3ce1",
      "claim_e47223f49ebf0e69",
      "claim_561a1d06e02ae001",
      "claim_0b829628830e2652",
      "claim_f0043edd51570008",
      "claim_1b40c4bd8c3b29c0",
      "claim_1d82b1a8456d67fe",
      "claim_59c460e67234bab6",
      "claim_7f0e74c33875b475",
      "claim_544807da295a9c4e",
      "claim_d6d1bf9e2d9691e7",
      "claim_8ec0eca131ac7990",
      "claim_e5936fa5ee700987",
      "claim_595c41228eec06f4",
      "claim_62507886efa904cb",
      "claim_57981a3a0e310aa4",
      "claim_140dd3f99fbb95dd",
      "claim_5089edfe8a928490",
      "claim_f9d275e281d629cc",
      "claim_6013cd2896c791fa",
      "claim_c06acd2bf020ecb6",
      "claim_65a3fabce7a910ac",
      "claim_abf34a6f6e7fc7e0",
      "claim_c3af7497bed35cc0",
      "claim_2e0f375870ac9558",
      "claim_d31b4622c1ce86f1",
      "claim_6693394de81ab428",
      "claim_2d7d360d34a94a9b",
      "claim_ac60941e648e8bf3",
      "claim_12cb7e63f3170060",
      "claim_2d4406a66b5ebb02",
      "claim_ef8188598b2939ff",
      "claim_b29e0ccde426f1e3",
      "claim_2d5fb7db70e6d967",
      "claim_0a4597c5acae506c",
      "claim_c67dbab36688bafe",
      "claim_3bce95de91b81599",
      "claim_e9de88e1c07d09cd",
      "claim_2db4e52607bade74",
      "claim_2491b320cdb55569",
      "claim_f476441986b35258",
      "claim_7a2fdfa6a1ccedac",
      "claim_5d11e785d3617dcb",
      "claim_2482bd6258388444",
      "claim_29820a37b4626722",
      "claim_cdade556479a285e",
      "claim_a4d91fea4570b433",
      "claim_a1ce4c3441f65690",
      "claim_f912a25bafb080ea",
      "claim_628e79c9976beea4",
      "claim_16fe3d7a9c75d768",
      "claim_adc43189fcf47df7",
      "claim_cf552bc6296d53fc",
      "claim_5ec3c9d0e4383c1c",
      "claim_421cee6d6416041d",
      "claim_a4b69554a366a548",
      "claim_653fb5ae015f0b5c",
      "claim_4cf63c81dad30bfd",
      "claim_71ac00cf16ace7b5",
      "claim_86a7143b3b7372c1",
      "claim_2582176710536d6e",
      "claim_2ab2bd859a26c0e6",
      "claim_2858324349443fbd",
      "claim_63c3443f9ccd97a4",
      "claim_d96111766671cde0",
      "claim_325d8b1b8b2e9e47",
      "claim_7aa1cded19b94a22",
      "claim_19971f3254117785",
      "claim_8bfc258e4fc8e470",
      "claim_46df9bbcf81dfa6d",
      "claim_301aa6f63577ad9c",
      "claim_2955f0e40df6521d",
      "claim_c4cf34889c68825b",
      "claim_f9e0327fee13497e",
      "claim_9e4d17f5bf0df636",
      "claim_d23b3339a7ad47ab",
      "claim_44f0bb28fda3a950",
      "claim_036906050bf970f9",
      "claim_07497e6ff4cc8732",
      "claim_46ec884f1570c873",
      "claim_1606aa71c3d515d4",
      "claim_423b4d729b57ad2b",
      "claim_dc1e1a5fcbe79ab2",
      "claim_a90df116f2a4eef6"
    ]
  }
}